vaulty/__init__.py
vaulty/auth.py
vaulty/client.py
vaulty/exceptions.py
vaulty/http.py
vaulty/logging.py
vaulty/models.py
vaulty/retry.py
vaulty/utils.py
vaulty/cli/__init__.py
vaulty/cli/config.py
vaulty/cli/main.py
vaulty/cli/output.py
vaulty/cli/utils.py
vaulty/cli/commands/__init__.py
vaulty/cli/commands/activities.py
vaulty/cli/commands/auth.py
vaulty/cli/commands/customers.py
vaulty/cli/commands/health.py
vaulty/cli/commands/projects.py
vaulty/cli/commands/secrets.py
vaulty/cli/commands/tokens.py
vaulty/resources/__init__.py
vaulty/resources/activities.py
vaulty/resources/customers.py
vaulty/resources/health.py
vaulty/resources/projects.py
vaulty/resources/secrets.py
vaulty/resources/tokens.py
vaulty_client-0.1.1.dist-info/licenses/LICENSE
vaulty_client-0.1.1.dist-info/METADATA
vaulty_client-0.1.1.dist-info/WHEEL
vaulty_client-0.1.1.dist-info/entry_points.txt
vaulty_client-0.1.1.dist-info/top_level.txt
vaulty_client-0.1.1.dist-info/RECORD
